jpl/slim/VERSION.txt
jpl/slim/__init__.py
jpl/slim/leaderboard.py
slim_leaderboard-0.0.0.dist-info/METADATA
slim_leaderboard-0.0.0.dist-info/WHEEL
slim_leaderboard-0.0.0.dist-info/entry_points.txt
slim_leaderboard-0.0.0.dist-info/licenses/LICENSE
slim_leaderboard-0.0.0.dist-info/RECORD
