Metadata-Version: 2.4
Name: slim-leaderboard
Version: 0.0.0
Summary: Tool to generate a scan report of SLIM best practices compliance
Project-URL: Homepage, https://github.com/SLIM/slim-leaderboard
Project-URL: Issues, https://github.com/SLIM/slim-leaderboard/issues
Author-email: Kyongsik Yun <kyongsik.yun@jpl.nasa.gov>, Rishi Verma <Rishi.Verma@jpl.nasa.gov>, Sean Kelly <kelly@seankelly.biz>
License:                                  Apache License
License-File: LICENSE
Keywords: ammos,automation,development,nasa,practice,report,slim,software
Classifier: Development Status :: 2 - Pre-Alpha
Classifier: Environment :: Console
Classifier: Intended Audience :: Developers
Classifier: Intended Audience :: Science/Research
Classifier: License :: OSI Approved :: Apache Software License
Classifier: Natural Language :: English
Classifier: Operating System :: OS Independent
Classifier: Programming Language :: Python :: 3
Requires-Python: >=3.7
Requires-Dist: requests-cache~=1.2.1
Requires-Dist: requests~=2.32.3
Requires-Dist: rich~=13.9.4
Requires-Dist: tqdm~=4.66.6
